zenpass/__init__.py
zenpass/__main__.py
zenpass/constant.py
zenpass/exception.py
zenpass/password.py
zenpass-1.0.5.dist-info/LICENSE
zenpass-1.0.5.dist-info/METADATA
zenpass-1.0.5.dist-info/WHEEL
zenpass-1.0.5.dist-info/entry_points.txt
zenpass-1.0.5.dist-info/top_level.txt
zenpass-1.0.5.dist-info/RECORD
