Metadata-Version: 2.1
Name: zenpass
Version: 1.0.5
Summary: To generate random and strong passwords.
Author-email: srg <srg.code@pm.me>
License: Apache License, Version 2.0
Project-URL: Homepage, https://github.com/codesrg/zenpass
Project-URL: Bug Tracker, https://github.com/codesrg/zenpass/issues
Keywords: zenpass,genpasswd
Classifier: Programming Language :: Python :: 3
Classifier: License :: OSI Approved :: Apache Software License
Classifier: Operating System :: OS Independent
Requires-Python: >=3.6
License-File: LICENSE
Requires-Dist: srutil
Requires-Dist: pyperclip
